{"strawberry_riseholme_lincoln_tbd_178_rgb.png547214":{"filename":"strawberry_riseholme_lincoln_tbd_178_rgb.png","size":"547214","regions":[{"shape_attributes":{"name":"polygon","all_points_x":[196,190,174,166,168,182,195,201,210,209,207],"all_points_y":[23,20,19,26,47,64,68,63,51,36,25]},"region_attributes":{"Hardness of Picking":"1","Degree of Ripeness":"0"}},{"shape_attributes":{"name":"polygon","all_points_x":[219,213,210,221,232,237,237,232],"all_points_y":[10,18,27,37,34,28,20,13]},"region_attributes":{"Hardness of Picking":"0","Degree of Ripeness":"0"}},{"shape_attributes":{"name":"polygon","all_points_x":[279,318,322,322,281],"all_points_y":[9,16,10,1,1]},"region_attributes":{"Hardness of Picking":"0","Degree of Ripeness":"0"}},{"shape_attributes":{"name":"polygon","all_points_x":[374,386,394,395,380,376,368],"all_points_y":[18,16,27,36,45,43,31]},"region_attributes":{"Hardness of Picking":"0","Degree of Ripeness":"3"}},{"shape_attributes":{"name":"polygon","all_points_x":[176,184,191,194,198,188,177],"all_points_y":[127,120,123,126,133,146,141]},"region_attributes":{"Hardness of Picking":"0","Degree of Ripeness":"4"}},{"shape_attributes":{"name":"polygon","all_points_x":[216,233,239,242,239,234,219,213,212],"all_points_y":[135,132,138,145,153,159,152,148,143]},"region_attributes":{"Hardness of Picking":"1","Degree of Ripeness":"3"}},{"shape_attributes":{"name":"polygon","all_points_x":[207,228,233,233,218,209,204,203],"all_points_y":[161,159,162,170,186,181,176,168]},"region_attributes":{"Hardness of Picking":"0","Degree of Ripeness":"2"}},{"shape_attributes":{"name":"polygon","all_points_x":[244,237,239,247,253,255,254],"all_points_y":[203,209,213,217,215,211,209]},"region_attributes":{"Hardness of Picking":"0","Degree of Ripeness":"4"}},{"shape_attributes":{"name":"polygon","all_points_x":[116,142,148,144,130,121,107,107,111],"all_points_y":[254,263,272,281,294,295,275,270,262]},"region_attributes":{"Hardness of Picking":"2","Degree of Ripeness":"3"}},{"shape_attributes":{"name":"polygon","all_points_x":[140,146,150,155,157,159,161,159,152,147,137,132,134],"all_points_y":[300,307,309,308,302,296,290,284,282,281,281,291,298]},"region_attributes":{"Hardness of Picking":"0","Degree of Ripeness":"0"}},{"shape_attributes":{"name":"polygon","all_points_x":[103,107,106,115,121,124,125,122,119,109,105],"all_points_y":[282,287,287,293,291,288,284,277,271,272,276]},"region_attributes":{"Hardness of Picking":"0","Degree of Ripeness":"0"}},{"shape_attributes":{"name":"polygon","all_points_x":[502,492,483,481,497,510,514,514],"all_points_y":[52,55,64,77,80,81,75,60]},"region_attributes":{"Hardness of Picking":"0","Degree of Ripeness":"3"}},{"shape_attributes":{"name":"polygon","all_points_x":[518,519,523,530,533,531,522,519],"all_points_y":[48,54,56,55,46,43,42,42]},"region_attributes":{"Hardness of Picking":"0","Degree of Ripeness":"0"}},{"shape_attributes":{"name":"polygon","all_points_x":[463,464,483,488,471,462,455,453],"all_points_y":[95,95,99,111,131,127,111,103]},"region_attributes":{"Hardness of Picking":"0","Degree of Ripeness":"3"}},{"shape_attributes":{"name":"polygon","all_points_x":[489,497,505,511,512,512,513,509,494,481,478],"all_points_y":[89,94,94,91,85,75,65,55,57,64,68]},"region_attributes":{"Hardness of Picking":"0","Degree of Ripeness":"3"}},{"shape_attributes":{"name":"polygon","all_points_x":[516,519,533,535,539,537,532],"all_points_y":[105,91,90,97,109,114,116]},"region_attributes":{"Hardness of Picking":"0","Degree of Ripeness":"0"}},{"shape_attributes":{"name":"polygon","all_points_x":[553,539,537,551,557,561,562,562],"all_points_y":[78,86,92,101,102,97,88,79]},"region_attributes":{"Hardness of Picking":"0","Degree of Ripeness":"0"}},{"shape_attributes":{"name":"polygon","all_points_x":[544,553,572,579,576,576,573,545],"all_points_y":[159,148,141,151,167,181,184,168]},"region_attributes":{"Hardness of Picking":"1","Degree of Ripeness":"0"}},{"shape_attributes":{"name":"polygon","all_points_x":[464,457,459,463,474,478,476,475],"all_points_y":[178,184,192,198,199,188,184,183]},"region_attributes":{"Hardness of Picking":"0","Degree of Ripeness":"0"}},{"shape_attributes":{"name":"polygon","all_points_x":[508,531,534,532,511,506,501],"all_points_y":[199,208,216,224,236,233,211]},"region_attributes":{"Hardness of Picking":"0","Degree of Ripeness":"3"}},{"shape_attributes":{"name":"polygon","all_points_x":[435,450,451,451,440,433,427,421,424],"all_points_y":[194,201,209,214,227,225,218,205,197]},"region_attributes":{"Hardness of Picking":"0","Degree of Ripeness":"1"}},{"shape_attributes":{"name":"polygon","all_points_x":[478,490,496,498,493,484,472,468,464,463,469],"all_points_y":[225,228,233,243,249,257,260,251,243,236,226]},"region_attributes":{"Hardness of Picking":"0","Degree of Ripeness":"3"}},{"shape_attributes":{"name":"polygon","all_points_x":[457,461,469,473,472,467,461,454,452],"all_points_y":[273,275,277,282,290,295,297,294,284]},"region_attributes":{"Hardness of Picking":"0","Degree of Ripeness":"0"}},{"shape_attributes":{"name":"polygon","all_points_x":[412,433,434,432,419,415,408,404,401,403],"all_points_y":[319,329,337,346,355,355,351,342,333,327]},"region_attributes":{"Hardness of Picking":"0","Degree of Ripeness":"3"}},{"shape_attributes":{"name":"polygon","all_points_x":[545,554,556,551,545,538,531,529],"all_points_y":[249,261,269,280,282,280,270,267]},"region_attributes":{"Hardness of Picking":"0","Degree of Ripeness":"3"}},{"shape_attributes":{"name":"polygon","all_points_x":[558,563,575,570,563,558],"all_points_y":[274,277,265,258,259,266]},"region_attributes":{"Hardness of Picking":"0","Degree of Ripeness":"0"}}],"file_attributes":{}},"strawberry_riseholme_lincoln_tbd_177_rgb.png528603":{"filename":"strawberry_riseholme_lincoln_tbd_177_rgb.png","size":"528603","regions":[{"shape_attributes":{"name":"polygon","all_points_x":[39,39,53,59,61,58,56,45,34,30,32],"all_points_y":[48,48,49,54,62,70,75,80,69,56,52]},"region_attributes":{"Hardness of Picking":"0","Degree of Ripeness":"3"}},{"shape_attributes":{"name":"polygon","all_points_x":[181,182,196,200,197,191,182,177,174,175],"all_points_y":[211,209,216,221,233,237,238,232,221,216]},"region_attributes":{"Hardness of Picking":"0","Degree of Ripeness":"3"}},{"shape_attributes":{"name":"polygon","all_points_x":[248,265,271,272,267,262,255,251,246],"all_points_y":[160,154,162,170,181,183,183,179,170]},"region_attributes":{"Hardness of Picking":"0","Degree of Ripeness":"1"}},{"shape_attributes":{"name":"polygon","all_points_x":[257,271,273,272,259,255,254],"all_points_y":[206,207,212,220,227,226,219]},"region_attributes":{"Hardness of Picking":"0","Degree of Ripeness":"0"}},{"shape_attributes":{"name":"polygon","all_points_x":[301,320,324,314,300,292,288,290],"all_points_y":[132,141,152,163,171,167,151,137]},"region_attributes":{"Hardness of Picking":"0","Degree of Ripeness":"3"}},{"shape_attributes":{"name":"polygon","all_points_x":[328,339,345,348,347,342,339,328,315,312,316],"all_points_y":[158,154,157,165,178,189,190,188,177,170,161]},"region_attributes":{"Hardness of Picking":"0","Degree of Ripeness":"3"}},{"shape_attributes":{"name":"polygon","all_points_x":[293,293,301,308,306,295,288,288],"all_points_y":[80,80,80,85,100,104,101,86]},"region_attributes":{"Hardness of Picking":"0","Degree of Ripeness":"0"}},{"shape_attributes":{"name":"polygon","all_points_x":[387,396,407,410,399,392,385],"all_points_y":[115,113,116,122,139,139,127]},"region_attributes":{"Hardness of Picking":"0","Degree of Ripeness":"0"}},{"shape_attributes":{"name":"polygon","all_points_x":[391,406,408,394,390,386,386],"all_points_y":[174,180,188,201,200,197,186]},"region_attributes":{"Hardness of Picking":"0","Degree of Ripeness":"2"}},{"shape_attributes":{"name":"polygon","all_points_x":[492,502,514,506,503,494,484,482],"all_points_y":[185,185,202,217,220,216,204,194]},"region_attributes":{"Hardness of Picking":"0","Degree of Ripeness":"3"}}],"file_attributes":{}}}